<?xml version="1.0" encoding="UTF-8"?>
<art>
<locacion>
		<imagen>imagenes/img1.jpg</imagen>
	</locacion>
<locacion>
		<imagen>imagenes/img1.jpg</imagen>
	</locacion>
<locacion>
		<imagen>imagenes/img2.jpg</imagen>
	</locacion>
<locacion>
		<imagen>imagenes/img3.jpg</imagen>
	</locacion>
<locacion>
		<imagen>imagenes/img4.jpg</imagen>
	</locacion>
<locacion>
		<imagen>imagenes/img5.jpg</imagen>
	</locacion>
<locacion>
		<imagen>imagenes/img6.jpg</imagen>
	</locacion>
<locacion>
		<imagen>imagenes/img7.jpg</imagen>
	</locacion>
<locacion>
		<imagen>imagenes/img8.jpg</imagen>
	</locacion>
<locacion>
		<imagen>imagenes/img9.jpg</imagen>
	</locacion>
<locacion>
		<imagen>imagenes/img10.jpg</imagen>
	</locacion>
<locacion>
		<imagen>imagenes/img11.jpg</imagen>
	</locacion>
<locacion>
		<imagen>imagenes/img12.jpg</imagen>
	</locacion>
<locacion>
		<imagen>imagenes/img13.jpg</imagen>
	</locacion>
<locacion>
		<imagen>imagenes/img14.jpg</imagen>
	</locacion>
<locacion>
		<imagen>imagenes/img15.jpg</imagen>
	</locacion>
<locacion>
		<imagen>imagenes/img16.jpg</imagen>
	</locacion>
<locacion>
		<imagen>imagenes/img17.jpg</imagen>
	</locacion>
<locacion>
		<imagen>imagenes/img18.jpg</imagen>
	</locacion>
<locacion>
		<imagen>imagenes/img19.jpg</imagen>
	</locacion>
<locacion>
		<imagen>imagenes/img20.jpg</imagen>
	</locacion>
<locacion>
		<imagen>imagenes/img21.jpg</imagen>
	</locacion>
</art>





